{
  "applications": "*",
  "changelogDate": "20220807085117",
  "dto": "no",
  "embedded": false,
  "entityTableName": "teacher",
  "fields": [
    {
      "fieldName": "id",
      "fieldType": "Long"
    },
    {
      "fieldName": "firstName",
      "fieldType": "String"
    },
    {
      "fieldName": "lastName",
      "fieldType": "String"
    },
    {
      "fieldName": "email",
      "fieldType": "String"
    },
    {
      "fieldName": "phoneNumber",
      "fieldType": "String"
    }
  ],
  "fluentMethods": true,
  "jpaMetamodelFiltering": false,
  "name": "Teacher",
  "pagination": "no",
  "readOnly": false,
  "relationships": [],
  "service": "no"
}
